{
  "scenario_id": "qlog-5030",
  "query": "db size has not reduced at all: -rw-r--r-- 1 vscode vscode 206753792 Mar 31 14:27 unimatrix.db",
  "profiles": {
    "combined-ppr-enabled": {
      "entries": [
        {
          "id": 3591,
          "title": "ADR-001 col-029: EDGE_SOURCE_NLI Named Constant in unimatrix-store",
          "category": "decision",
          "final_score": 0.4306455336922037,
          "similarity": 0.3283417224884033,
          "confidence": 0.6284068450382626,
          "status": "Active",
          "nli_rerank_delta": null
        },
        {
          "id": 427,
          "title": "Fixed-Width Feature Vector with Reserved Slots (SignalDigest)",
          "category": "pattern",
          "final_score": 0.4275512542801492,
          "similarity": 0.3466418981552124,
          "confidence": 0.593864978538673,
          "status": "Active",
          "nli_rerank_delta": null
        },
        {
          "id": 1567,
          "title": "Retrospective findings: crt-018b",
          "category": "lesson-learned",
          "final_score": 0.42055873260547294,
          "similarity": 0.31625401973724365,
          "confidence": 0.6182965317330787,
          "status": "Active",
          "nli_rerank_delta": null
        },
        {
          "id": 2661,
          "title": "Snapshot commands must copy all storage artifacts, not just the primary database",
          "category": "lesson-learned",
          "final_score": 0.39937760627117225,
          "similarity": 0.32797181606292725,
          "confidence": 0.5440651940747145,
          "status": "Active",
          "nli_rerank_delta": null
        },
        {
          "id": 3885,
          "title": "unimatrix-store sqlite types: lesson-learned",
          "category": "lesson-learned",
          "final_score": 0.3892468057856723,
          "similarity": 0.32927441596984863,
          "confidence": 0.5147064500327555,
          "status": "Active",
          "nli_rerank_delta": null
        }
      ],
      "latency_ms": 10,
      "p_at_k": 0.0,
      "mrr": 0.0,
      "cc_at_k": 0.6,
      "icd": 0.9502705392332347
    },
    "combined-ppr-disabled": {
      "entries": [
        {
          "id": 3591,
          "title": "ADR-001 col-029: EDGE_SOURCE_NLI Named Constant in unimatrix-store",
          "category": "decision",
          "final_score": 0.4306455336922037,
          "similarity": 0.3283417224884033,
          "confidence": 0.6284068450382626,
          "status": "Active",
          "nli_rerank_delta": null
        },
        {
          "id": 427,
          "title": "Fixed-Width Feature Vector with Reserved Slots (SignalDigest)",
          "category": "pattern",
          "final_score": 0.4275512542801492,
          "similarity": 0.3466418981552124,
          "confidence": 0.593864978538673,
          "status": "Active",
          "nli_rerank_delta": null
        },
        {
          "id": 1567,
          "title": "Retrospective findings: crt-018b",
          "category": "lesson-learned",
          "final_score": 0.42055873260547294,
          "similarity": 0.31625401973724365,
          "confidence": 0.6182965317330787,
          "status": "Active",
          "nli_rerank_delta": null
        },
        {
          "id": 2661,
          "title": "Snapshot commands must copy all storage artifacts, not just the primary database",
          "category": "lesson-learned",
          "final_score": 0.39937760627117225,
          "similarity": 0.32797181606292725,
          "confidence": 0.5440651940747145,
          "status": "Active",
          "nli_rerank_delta": null
        },
        {
          "id": 3885,
          "title": "unimatrix-store sqlite types: lesson-learned",
          "category": "lesson-learned",
          "final_score": 0.3892468057856723,
          "similarity": 0.32927441596984863,
          "confidence": 0.5147064500327555,
          "status": "Active",
          "nli_rerank_delta": null
        }
      ],
      "latency_ms": 8,
      "p_at_k": 0.0,
      "mrr": 0.0,
      "cc_at_k": 0.6,
      "icd": 0.9502705392332347
    }
  },
  "comparison": {
    "kendall_tau": 1.0,
    "rank_changes": [],
    "mrr_delta": 0.0,
    "p_at_k_delta": 0.0,
    "latency_overhead_ms": 2,
    "cc_at_k_delta": 0.0,
    "icd_delta": 0.0
  },
  "phase": null
}