{
  "scenario_id": "qlog-2197",
  "query": "now complete any remaining steps on 359 for any cleanup",
  "profiles": {
    "combined-ppr-disabled": {
      "entries": [
        {
          "id": 3002,
          "title": "ADR-005 crt-025: outcome Category Retirement — Ingest Block Only, No Data Deletion",
          "category": "decision",
          "final_score": 0.46642586302452227,
          "similarity": 0.4015178680419922,
          "confidence": 0.6209875310065719,
          "status": "Active",
          "nli_rerank_delta": null
        },
        {
          "id": 722,
          "title": "Worktree cleanup is retro's responsibility, not implementation's",
          "category": "lesson-learned",
          "final_score": 0.44282158109945735,
          "similarity": 0.3835557699203491,
          "confidence": 0.5825789059551714,
          "status": "Active",
          "nli_rerank_delta": null
        },
        {
          "id": 820,
          "title": "ADR-010-003: Backfill topic_deliveries in Main Migration Transaction",
          "category": "decision",
          "final_score": 0.4335323791881893,
          "similarity": 0.37912124395370483,
          "confidence": 0.5637003950055072,
          "status": "Active",
          "nli_rerank_delta": null
        },
        {
          "id": 367,
          "title": "Two-phase migration (add-then-subtract) eliminates rework in backend replacements",
          "category": "lesson-learned",
          "final_score": 0.43218239989589424,
          "similarity": 0.35681164264678955,
          "confidence": 0.5919070245077281,
          "status": "Active",
          "nli_rerank_delta": null
        },
        {
          "id": 3767,
          "title": "ADR-002 correction: prune pass and heal pass are also unconditional since bugfix-444 (supersedes #3559, #178)",
          "category": "decision",
          "final_score": 0.42072751227513827,
          "similarity": 0.3808929920196533,
          "confidence": 0.5264132590044422,
          "status": "Active",
          "nli_rerank_delta": null
        }
      ],
      "latency_ms": 6,
      "p_at_k": 0.0,
      "mrr": 0.0,
      "cc_at_k": 0.4,
      "icd": 0.6730116670092565
    },
    "combined-ppr-enabled": {
      "entries": [
        {
          "id": 3002,
          "title": "ADR-005 crt-025: outcome Category Retirement — Ingest Block Only, No Data Deletion",
          "category": "decision",
          "final_score": 0.46642586302452227,
          "similarity": 0.4015178680419922,
          "confidence": 0.6209875310065719,
          "status": "Active",
          "nli_rerank_delta": null
        },
        {
          "id": 722,
          "title": "Worktree cleanup is retro's responsibility, not implementation's",
          "category": "lesson-learned",
          "final_score": 0.44282158109945735,
          "similarity": 0.3835557699203491,
          "confidence": 0.5825789059551714,
          "status": "Active",
          "nli_rerank_delta": null
        },
        {
          "id": 820,
          "title": "ADR-010-003: Backfill topic_deliveries in Main Migration Transaction",
          "category": "decision",
          "final_score": 0.4335323791881893,
          "similarity": 0.37912124395370483,
          "confidence": 0.5637003950055072,
          "status": "Active",
          "nli_rerank_delta": null
        },
        {
          "id": 367,
          "title": "Two-phase migration (add-then-subtract) eliminates rework in backend replacements",
          "category": "lesson-learned",
          "final_score": 0.43218239989589424,
          "similarity": 0.35681164264678955,
          "confidence": 0.5919070245077281,
          "status": "Active",
          "nli_rerank_delta": null
        },
        {
          "id": 3767,
          "title": "ADR-002 correction: prune pass and heal pass are also unconditional since bugfix-444 (supersedes #3559, #178)",
          "category": "decision",
          "final_score": 0.42072751227513827,
          "similarity": 0.3808929920196533,
          "confidence": 0.5264132590044422,
          "status": "Active",
          "nli_rerank_delta": null
        }
      ],
      "latency_ms": 7,
      "p_at_k": 0.0,
      "mrr": 0.0,
      "cc_at_k": 0.4,
      "icd": 0.6730116670092565
    }
  },
  "comparison": {
    "kendall_tau": 1.0,
    "rank_changes": [],
    "mrr_delta": 0.0,
    "p_at_k_delta": 0.0,
    "latency_overhead_ms": 1,
    "cc_at_k_delta": 0.0,
    "icd_delta": 0.0
  },
  "phase": null
}