{
  "scenario_id": "obs-364cb76e-1774443784000",
  "query": "tracing subscriber RUST_LOG filter target",
  "profiles": {
    "combined-ppr-enabled": {
      "entries": [
        {
          "id": 3453,
          "title": "tracing-subscriber with_env_filter(&str) ignores RUST_LOG — use EnvFilter::try_from_default_env() for runtime filter control",
          "category": "lesson-learned",
          "final_score": 0.6443774366115439,
          "similarity": 0.7755832076072693,
          "confidence": 0.5696198885066635,
          "status": "Active",
          "nli_rerank_delta": null
        },
        {
          "id": 3465,
          "title": "How to initialize tracing-subscriber in a new unimatrix-server entry point (tokio_main_*)",
          "category": "procedure",
          "final_score": 0.6214399714015465,
          "similarity": 0.7558903098106384,
          "confidence": 0.535493765503286,
          "status": "Active",
          "nli_rerank_delta": null
        },
        {
          "id": 3468,
          "title": "ADR: tracing-subscriber initialized with EnvFilter::try_from_default_env() at all server entry points — static &str filter forbidden",
          "category": "decision",
          "final_score": 0.5718483304695509,
          "similarity": 0.6901892423629761,
          "confidence": 0.4947465507559583,
          "status": "Active",
          "nli_rerank_delta": null
        },
        {
          "id": 3467,
          "title": "ADR: UDS observation logs use synthetic target \"unimatrix_server::obs\" for independent operator control",
          "category": "decision",
          "final_score": 0.5138622480350742,
          "similarity": 0.5578489899635315,
          "confidence": 0.5264132590044422,
          "status": "Active",
          "nli_rerank_delta": null
        },
        {
          "id": 3464,
          "title": "Implementation checklist items from approved design must be enumerated in the rust-dev spawn prompt — not left implicit in the investigator report",
          "category": "lesson-learned",
          "final_score": 0.47236615215141264,
          "similarity": 0.5011734366416931,
          "confidence": 0.4947460749228443,
          "status": "Active",
          "nli_rerank_delta": null
        }
      ],
      "latency_ms": 4,
      "p_at_k": 0.0,
      "mrr": 0.0,
      "cc_at_k": 0.6,
      "icd": 1.0549201679861442
    },
    "combined-ppr-disabled": {
      "entries": [
        {
          "id": 3453,
          "title": "tracing-subscriber with_env_filter(&str) ignores RUST_LOG — use EnvFilter::try_from_default_env() for runtime filter control",
          "category": "lesson-learned",
          "final_score": 0.6443774366115439,
          "similarity": 0.7755832076072693,
          "confidence": 0.5696198885066635,
          "status": "Active",
          "nli_rerank_delta": null
        },
        {
          "id": 3465,
          "title": "How to initialize tracing-subscriber in a new unimatrix-server entry point (tokio_main_*)",
          "category": "procedure",
          "final_score": 0.6214399714015465,
          "similarity": 0.7558903098106384,
          "confidence": 0.535493765503286,
          "status": "Active",
          "nli_rerank_delta": null
        },
        {
          "id": 3468,
          "title": "ADR: tracing-subscriber initialized with EnvFilter::try_from_default_env() at all server entry points — static &str filter forbidden",
          "category": "decision",
          "final_score": 0.5718483304695509,
          "similarity": 0.6901892423629761,
          "confidence": 0.4947465507559583,
          "status": "Active",
          "nli_rerank_delta": null
        },
        {
          "id": 3467,
          "title": "ADR: UDS observation logs use synthetic target \"unimatrix_server::obs\" for independent operator control",
          "category": "decision",
          "final_score": 0.5138622480350742,
          "similarity": 0.5578489899635315,
          "confidence": 0.5264132590044422,
          "status": "Active",
          "nli_rerank_delta": null
        },
        {
          "id": 3464,
          "title": "Implementation checklist items from approved design must be enumerated in the rust-dev spawn prompt — not left implicit in the investigator report",
          "category": "lesson-learned",
          "final_score": 0.47236615215141264,
          "similarity": 0.5011734366416931,
          "confidence": 0.4947460749228443,
          "status": "Active",
          "nli_rerank_delta": null
        }
      ],
      "latency_ms": 4,
      "p_at_k": 0.0,
      "mrr": 0.0,
      "cc_at_k": 0.6,
      "icd": 1.0549201679861442
    }
  },
  "comparison": {
    "kendall_tau": 1.0,
    "rank_changes": [],
    "mrr_delta": 0.0,
    "p_at_k_delta": 0.0,
    "latency_overhead_ms": 0,
    "cc_at_k_delta": 0.0,
    "icd_delta": 0.0
  },
  "phase": null
}